ipscan/__init__.py
ipscan/fping.py
ipscan/sarp.py
ipscan/sping.py
ipscan-1.3.1.dist-info/licenses/LICENSE
ipscan-1.3.1.dist-info/METADATA
ipscan-1.3.1.dist-info/WHEEL
ipscan-1.3.1.dist-info/entry_points.txt
ipscan-1.3.1.dist-info/top_level.txt
ipscan-1.3.1.dist-info/RECORD
