Metadata-Version: 2.4
Name: ipscan
Version: 1.3.1
Summary: Fast IP scanner — multithreaded Ping and ARP scanning
Home-page: https://github.com/Wing9897/ipscan.git
Author: Wing
Author-email: tomt99688@gmail.com
License: MIT
Project-URL: Source, https://github.com/Wing9897/ipscan
Project-URL: English README, https://github.com/Wing9897/ipscan/blob/main/README.md
Project-URL: 繁體中文 README, https://github.com/Wing9897/ipscan/blob/main/README.zh-TW.md
Keywords: ip scan ping arp network scanner
Classifier: Development Status :: 5 - Production/Stable
Classifier: Operating System :: Microsoft :: Windows
Classifier: Operating System :: POSIX :: Linux
Classifier: Operating System :: MacOS
Classifier: Programming Language :: Python :: 3
Classifier: Programming Language :: Python :: 3.7
Classifier: Programming Language :: Python :: 3.8
Classifier: Programming Language :: Python :: 3.9
Classifier: Programming Language :: Python :: 3.10
Classifier: Programming Language :: Python :: 3.11
Classifier: Programming Language :: Python :: 3.12
Classifier: Topic :: System :: Networking
Classifier: Natural Language :: English
Classifier: Natural Language :: Chinese (Traditional)
Requires-Python: >=3.7
License-File: LICENSE
Requires-Dist: tqdm>=4.60.0
Requires-Dist: scapy>=2.4.5
Provides-Extra: windows
Requires-Dist: ping3>=4.0.0; extra == "windows"
Dynamic: author
Dynamic: author-email
Dynamic: classifier
Dynamic: description
Dynamic: description-content-type
Dynamic: home-page
Dynamic: keywords
Dynamic: license
Dynamic: license-file
Dynamic: project-url
Dynamic: provides-extra
Dynamic: requires-dist
Dynamic: requires-python
Dynamic: summary
